{
  "project_info": {
    "project_number": "616097072274",
    "firebase_url": "https://finalurinew-default-rtdb.firebaseio.com",
    "project_id": "finalurinew",
    "storage_bucket": "finalurinew.appspot.com"
  },
  "client": [
    {
      "client_info": {
        "mobilesdk_app_id": "1:616097072274:android:5475b5d1fe96bb3382d24b",
        "android_client_info": {
          "package_name": "com.example.firebaserecyclerviewkotlin"
        }
      },
      "oauth_client": [
        {
          "client_id": "616097072274-hsesd0ll3rje8pp36prk07uvli2s6pc2.apps.googleusercontent.com",
          "client_type": 3
        }
      ],
      "api_key": [
        {
          "current_key": "AIzaSyA3c9S2GyyknRYB1LDr9H6braNsIOnwQWI"
        }
      ],
      "services": {
        "appinvite_service": {
          "other_platform_oauth_client": [
            {
              "client_id": "616097072274-hsesd0ll3rje8pp36prk07uvli2s6pc2.apps.googleusercontent.com",
              "client_type": 3
            }
          ]
        }
      }
    }
  ],
  "configuration_version": "1"
}